setup.py
test_set_sdk.egg-info/PKG-INFO
test_set_sdk.egg-info/SOURCES.txt
test_set_sdk.egg-info/dependency_links.txt
test_set_sdk.egg-info/requires.txt
test_set_sdk.egg-info/top_level.txt
testsetup/__init__.py
testsetup/testcl/__init__.py
testsetup/testcl/test1.py
testsetup/testcl/test_01.py